maps.py
maps_restaurants-0.0.1.dist-info/LICENCE
maps_restaurants-0.0.1.dist-info/METADATA
maps_restaurants-0.0.1.dist-info/WHEEL
maps_restaurants-0.0.1.dist-info/top_level.txt
maps_restaurants-0.0.1.dist-info/RECORD
